fdcalls/__init__.py
fdcalls/fdcalls.py
fdcalls-1.4.dist-info/METADATA
fdcalls-1.4.dist-info/WHEEL
fdcalls-1.4.dist-info/entry_points.txt
fdcalls-1.4.dist-info/top_level.txt
fdcalls-1.4.dist-info/RECORD
