Metadata-Version: 2.1
Name: fdcalls
Version: 1.4
Summary: help view dangerous function calls across files
Home-page: UNKNOWN
Author: fxc
Author-email: FXC030618@outlook.com
License: UNKNOWN
Platform: UNKNOWN
Requires-Python: >=3.7
Requires-Dist: r2pipe (>=1.8.0)
